<?xml version="1.0" encoding="utf-8" ?>
<dwsync>
<file name="help.html" server="www.beta.gazettejournal.net/public_html/" local="128540530800000000" remote="128540530800000000" />
<file name="splash.html" server="www.beta.gazettejournal.net/public_html/" local="128540530800000000" remote="128540530800000000" />
<file name="styles.ini" server="www.beta.gazettejournal.net/public_html/" local="128540530800000000" remote="128540530800000000" />
<file name="syndicate.js" server="www.beta.gazettejournal.net/public_html/" local="128540530800000000" remote="128540530800000000" />
<file name="webfeed.html" server="www.beta.gazettejournal.net/public_html/" local="128540530800000000" remote="128540530800000000" />
<file name="wizard_menus.html" server="www.beta.gazettejournal.net/public_html/" local="128540530800000000" remote="128540530800000000" />
<file name="help.html" server="beta.gazettejournal.net/public_html/" local="128540530800000000" remote="128540530800000000" />
<file name="splash.html" server="beta.gazettejournal.net/public_html/" local="128540530800000000" remote="128540530800000000" />
<file name="styles.ini" server="beta.gazettejournal.net/public_html/" local="128540530800000000" remote="128540530800000000" />
<file name="syndicate.js" server="beta.gazettejournal.net/public_html/" local="128540530800000000" remote="128540530800000000" />
<file name="webfeed.html" server="beta.gazettejournal.net/public_html/" local="128540530800000000" remote="128540530800000000" />
<file name="wizard_menus.html" server="beta.gazettejournal.net/public_html/" local="128540530800000000" remote="128540530800000000" />
</dwsync>